piscesORM/__init__.py
piscesORM/_setting.py
piscesORM/base.py
piscesORM/errors.py
piscesORM/table.py
piscesorm-0.0.5.dist-info/licenses/LICENSE
piscesorm-0.0.5.dist-info/METADATA
piscesorm-0.0.5.dist-info/WHEEL
piscesorm-0.0.5.dist-info/top_level.txt
piscesorm-0.0.5.dist-info/RECORD
