Metadata-Version: 2.4
Name: PiscesORM
Version: 0.0.5
Summary: A lightweight, easy-used ORM for Python
Author-email: DK-Night <yuchen920707@gmail.com>
License-Expression: MIT
Project-URL: Homepage, https://github.com/DKNight-9207/piscesORM
Requires-Python: >=3.10
License-File: LICENSE
Requires-Dist: aiosqlite
Dynamic: license-file
